MagicCNKI/__init__.py
MagicCNKI/config.py
MagicCNKI/magic_cnki.py
MagicCNKI/data/user_agents.txt
MagicCNKI-0.0.1.dist-info/METADATA
MagicCNKI-0.0.1.dist-info/RECORD
MagicCNKI-0.0.1.dist-info/WHEEL
MagicCNKI-0.0.1.dist-info/top_level.txt
